{
  "status": 200,
  "data": {
    "next_to_go_ids": [
      "06579619-a9fa-4c9b-ae20-1d6c01f6ba88",
      "a455092e-071b-4412-8d5b-547832f77f83",
      "03b12f1e-1f70-4098-ae61-9e2e046e16e0",
      "997520e0-6554-439a-ab6c-7d67130df031",
      "b2f70aec-f181-44b7-b3ab-7673d31cfdf6",
      "439c768b-5bc3-41c9-86bf-4bb8b1d6bc19",
      "721e060a-1f90-4217-a80d-41333cd301d4",
      "77139d78-2067-4e51-b34f-846fb7e70266",
      "81560dea-c8fb-4ad4-bfc8-f2d0474e85c7",
      "617158ac-2ac9-4a0d-875d-c9f0b2827a6d"
    ],
    "race_summaries": {
      "03b12f1e-1f70-4098-ae61-9e2e046e16e0": {
        "race_id": "03b12f1e-1f70-4098-ae61-9e2e046e16e0",
        "race_name": "Race 9",
        "race_number": 9,
        "meeting_id": "217f5f09-f0ee-4669-929c-032df9407f3c",
        "meeting_name": "Yonkers Raceway",
        "category_id": "161d9be2-e909-4326-8c2c-35ed71fb460b",
        "advertised_start": {
          "seconds": 1748310360
        },
        "race_form": {
          "distance": 1609,
          "distance_type": {
            "id": "570775ae-09ec-42d5-989d-7c8f06366aa7",
            "name": "Metres",
            "short_name": "m"
          },
          "distance_type_id": "570775ae-09ec-42d5-989d-7c8f06366aa7",
          "track_condition": {
            "id": "1db9cab0-b747-11ea-80cf-6a390f79827e",
            "name": "Fast",
            "short_name": "fast"
          },
          "track_condition_id": "1db9cab0-b747-11ea-80cf-6a390f79827e",
          "weather": {
            "id": "08e5f78c-1a36-11eb-9269-cef03e67f1a3",
            "name": "FINE",
            "short_name": "fine",
            "icon_uri": "FINE"
          },
          "weather_id": "08e5f78c-1a36-11eb-9269-cef03e67f1a3",
          "additional_data": "{\"revealed_race_info\":{\"track_name\":\"Yonkers Raceway\",\"state\":\"NY\",\"country\":\"USA\",\"number\":9,\"race_name\":\"Race 9\",\"time\":\"2025-05-27T01:46:00Z\",\"class\":\"3-6YO30CLM\",\"start_type\":\"Mobile\",\"prizemonies\":{\"total_value\":28125},\"localised_prizemonies\":{\"AUD\":{\"total_value\":28125},\"NZD\":{\"total_value\":30375}},\"rail_position\":\"\",\"track_direction\":\"Right\",\"track_surface\":\"All Weather\",\"group\":\"\",\"gait\":\"P\",\"track_home_straight_metres\":0,\"track_circumference\":0}}",
          "generated": 1,
          "silk_base_url": "drr38safykj6s.cloudfront.net"
        },
        "venue_id": "38708866-f2be-47c3-a5c8-fd12cb7b4364",
        "venue_name": "Yonkers Raceway",
        "venue_state": "NY",
        "venue_country": "USA"
      },
      "06579619-a9fa-4c9b-ae20-1d6c01f6ba88": {
        "race_id": "06579619-a9fa-4c9b-ae20-1d6c01f6ba88",
        "race_name": "Race 9",
        "race_number": 9,
        "meeting_id": "7672104f-cbe3-4b61-8ca9-a6d34b6e4939",
        "meeting_name": "Hoosier Park",
        "category_id": "161d9be2-e909-4326-8c2c-35ed71fb460b",
        "advertised_start": {
          "seconds": 1748309760
        },
        "race_form": {
          "distance": 1609,
          "distance_type": {
            "id": "570775ae-09ec-42d5-989d-7c8f06366aa7",
            "name": "Metres",
            "short_name": "m"
          },
          "distance_type_id": "570775ae-09ec-42d5-989d-7c8f06366aa7",
          "track_condition": {
            "id": "10a14653-a33d-11e7-810d-0a1a4ae29bd2",
            "name": "Good",
            "short_name": "good"
          },
          "track_condition_id": "10a14653-a33d-11e7-810d-0a1a4ae29bd2",
          "additional_data": "{\"revealed_race_info\":{\"track_name\":\"Hoosier Park\",\"state\":\"IN\",\"country\":\"USA\",\"number\":9,\"race_name\":\"Race 9\",\"time\":\"2025-05-27T01:36:00Z\",\"class\":\"ISS-3yF\",\"start_type\":\"Mobile\",\"prizemonies\":{\"total_value\":77344},\"localised_prizemonies\":{\"AUD\":{\"total_value\":77344},\"NZD\":{\"total_value\":83532}},\"rail_position\":\"\",\"track_direction\":\"Left\",\"track_surface\":\"All Weather\",\"group\":\"\",\"gait\":\"T\",\"track_home_straight_metres\":0,\"track_circumference\":0}}",
          "generated": 1,
          "silk_base_url": "drr38safykj6s.cloudfront.net"
        },
        "venue_id": "4f7d90ce-9d88-4bdd-9b78-3f0199b1afcd",
        "venue_name": "Hoosier Park",
        "venue_state": "IN",
        "venue_country": "USA"
      },
      "439c768b-5bc3-41c9-86bf-4bb8b1d6bc19": {
        "race_id": "439c768b-5bc3-41c9-86bf-4bb8b1d6bc19",
        "race_name": "Race 8 - Maiden Claiming",
        "race_number": 8,
        "meeting_id": "f8c92aeb-a4eb-407d-b16c-17db28fff98a",
        "meeting_name": "Mountaineer Park",
        "category_id": "4a2788f8-e825-4d36-9894-efd4baf1cfae",
        "advertised_start": {
          "seconds": 1748310900
        },
        "race_form": {
          "distance": 1207,
          "distance_type": {
            "id": "570775ae-09ec-42d5-989d-7c8f06366aa7",
            "name": "Metres",
            "short_name": "m"
          },
          "distance_type_id": "570775ae-09ec-42d5-989d-7c8f06366aa7",
          "track_condition": {
            "id": "1db9cab0-b747-11ea-80cf-6a390f79827e",
            "name": "Fast",
            "short_name": "fast"
          },
          "track_condition_id": "1db9cab0-b747-11ea-80cf-6a390f79827e",
          "weather": {
            "id": "5ba75165-3cec-11eb-88bb-36fbfdf5d97f",
            "name": "OCAST",
            "short_name": "ocast",
            "icon_uri": "OCAST"
          },
          "weather_id": "5ba75165-3cec-11eb-88bb-36fbfdf5d97f",
          "race_comment": "UAINTRIGHT (12) Finished strongly when 2nd last time at Thistledown. Marshall Mendez and Anthony Farrior are usually competitive together. Has the speed to overcome the wide draw. Can go on with it. CAME UP ROSES (5) Tailed off to finish 10th last run at this track. May see an upturn in form and back to a rise in trip. Has early speed and positions nicely. Should go close. HONESTLY (10) Kept running on late when 2nd beaten by 2L last start here and stepping back up in distance. Been in the money 2 from 2 attempts this campaign. Up to these. REVOCATA (4) Ran 5th last start here but returns to an increased distance. Luis Negron has a good track record with the Jose Luna Silva stable. Expecting to settle positively. Knockout chance in this.",
          "additional_data": "{\"revealed_race_info\":{\"track_name\":\"Mountaineer Park\",\"state\":\"WV\",\"country\":\"USA\",\"number\":8,\"race_name\":\"Race 8 - Maiden Claiming\",\"time\":\"2025-05-27T01:55:00Z\",\"class\":\"MDN CLM\",\"start_type\":\"\",\"prizemonies\":{\"total_value\":12031},\"localised_prizemonies\":{\"AUD\":{\"1st\":7580,\"2nd\":2406,\"3rd\":1203,\"4th\":842,\"total_value\":12031},\"NZD\":{\"1st\":8186,\"2nd\":2598,\"3rd\":1299,\"4th\":909,\"total_value\":12993}},\"rail_position\":\"\",\"track_direction\":\"Left\",\"track_surface\":\"Dirt\",\"group\":\"\",\"gait\":\"Gallop\",\"track_home_straight_metres\":0,\"track_circumference\":0}}",
          "generated": 1,
          "silk_base_url": "drr38safykj6s.cloudfront.net",
          "race_comment_alternative": "UAINTRIGHT (12) Finished strongly when 2nd last time at Thistledown. Marshall Mendez and Anthony Farrior are usually competitive together. Has the speed to overcome the wide draw. Can go on with it. CAME UP ROSES (5) Tailed off to finish 10th last run at this track. May see an upturn in form and back to a rise in trip. Has early speed and positions nicely. Should go close. HONESTLY (10) Kept running on late when 2nd beaten by 2L last start here and stepping back up in distance. Been in the money 2 from 2 attempts this campaign. Up to these. REVOCATA (4) Ran 5th last start here but returns to an increased distance. Luis Negron has a good track record with the Jose Luna Silva stable. Expecting to settle positively. Knockout chance in this."
        },
        "venue_id": "33612182-29fc-4ddd-91e6-6617d7289d2b",
        "venue_name": "Mountaineer Park",
        "venue_state": "WV",
        "venue_country": "USA"
      },
      "617158ac-2ac9-4a0d-875d-c9f0b2827a6d": {
        "race_id": "617158ac-2ac9-4a0d-875d-c9f0b2827a6d",
        "race_name": "Race 11",
        "race_number": 11,
        "meeting_id": "7672104f-cbe3-4b61-8ca9-a6d34b6e4939",
        "meeting_name": "Hoosier Park",
        "category_id": "161d9be2-e909-4326-8c2c-35ed71fb460b",
        "advertised_start": {
          "seconds": 1748311500
        },
        "race_form": {
          "distance": 1609,
          "distance_type": {
            "id": "570775ae-09ec-42d5-989d-7c8f06366aa7",
            "name": "Metres",
            "short_name": "m"
          },
          "distance_type_id": "570775ae-09ec-42d5-989d-7c8f06366aa7",
          "track_condition": {
            "id": "10a14653-a33d-11e7-810d-0a1a4ae29bd2",
            "name": "Good",
            "short_name": "good"
          },
          "track_condition_id": "10a14653-a33d-11e7-810d-0a1a4ae29bd2",
          "additional_data": "{\"revealed_race_info\":{\"track_name\":\"Hoosier Park\",\"state\":\"IN\",\"country\":\"USA\",\"number\":11,\"race_name\":\"Race 11\",\"time\":\"2025-05-27T02:05:00Z\",\"class\":\"ISS-3yC\",\"start_type\":\"Mobile\",\"prizemonies\":{\"total_value\":76562},\"localised_prizemonies\":{\"AUD\":{\"total_value\":76562},\"NZD\":{\"total_value\":82687}},\"rail_position\":\"\",\"track_direction\":\"Left\",\"track_surface\":\"All Weather\",\"group\":\"\",\"gait\":\"P\",\"track_home_straight_metres\":0,\"track_circumference\":0}}",
          "generated": 1,
          "silk_base_url": "drr38safykj6s.cloudfront.net"
        },
        "venue_id": "4f7d90ce-9d88-4bdd-9b78-3f0199b1afcd",
        "venue_name": "Hoosier Park",
        "venue_state": "IN",
        "venue_country": "USA"
      },
      "721e060a-1f90-4217-a80d-41333cd301d4": {
        "race_id": "721e060a-1f90-4217-a80d-41333cd301d4",
        "race_name": "Ladbrokes Same Race Multi Division1",
        "race_number": 1,
        "meeting_id": "95b99992-a050-4bef-a031-2484f14e69cc",
        "meeting_name": "Launceston",
        "category_id": "9daef0d7-bf3c-4f50-921d-8e818c60fe61",
        "advertised_start": {
          "seconds": 1748310900
        },
        "race_form": {
          "distance": 278,
          "distance_type": {
            "id": "570775ae-09ec-42d5-989d-7c8f06366aa7",
            "name": "Metres",
            "short_name": "m"
          },
          "distance_type_id": "570775ae-09ec-42d5-989d-7c8f06366aa7",
          "track_condition": {
            "id": "10a14653-a33d-11e7-810d-0a1a4ae29bd2",
            "name": "Good",
            "short_name": "good"
          },
          "track_condition_id": "10a14653-a33d-11e7-810d-0a1a4ae29bd2",
          "weather": {
            "id": "06ee9afc-025e-11ec-a4cc-4a1fbbf2f065",
            "name": "SHWRY",
            "short_name": "shwry",
            "icon_uri": "SHWRY"
          },
          "weather_id": "06ee9afc-025e-11ec-a4cc-4a1fbbf2f065",
          "race_comment": "KAMLOOPS (1) copped a check in the run and finished a well held 63 lengths eighth (20.83) last time in a Other at this track over 278m. Looks the one to beat on best. TAKES TIME (3) had been racing well with a Grade 6 win three back then placed next time before missing the frame latest at this track. Expected to bounce back to best. ANNDAR SHELLY (7) scored two back by a space then was last start always well back and could manage only a 14 length 7th at Hobart (27.24). Warrants plenty of respect. HAT TRICK HANNAH (4) cannot be overlooked following a recent top-three finish here at this distance.",
          "additional_data": "{\"revealed_race_info\":{\"track_name\":\"Launceston\",\"state\":\"TAS\",\"country\":\"AUS\",\"number\":1,\"race_name\":\"Ladbrokes Same Race Multi Division1\",\"time\":\"2025-05-27T01:55:00Z\",\"class\":\"6th Grade\",\"start_type\":\"\",\"prizemonies\":{\"total_value\":3395},\"localised_prizemonies\":{\"AUD\":{\"1st\":2300,\"2nd\":660,\"3rd\":325,\"4th\":110,\"total_value\":3395},\"NZD\":{\"1st\":2484,\"2nd\":713,\"3rd\":351,\"4th\":119,\"total_value\":3667}},\"rail_position\":\"\",\"track_direction\":\"Left\",\"track_surface\":\"All Weather\",\"group\":\"\",\"gait\":\"Gallop\",\"track_home_straight_metres\":0,\"track_circumference\":0}}",
          "generated": 1,
          "silk_base_url": "drr38safykj6s.cloudfront.net",
          "race_comment_alternative": "KAMLOOPS (1) copped a check in the run and finished a well held 63 lengths eighth (20.83) last time in a Other at this track over 278m. Looks the one to beat on best. TAKES TIME (3) had been racing well with a Grade 6 win three back then placed next time before missing the frame latest at this track. Expected to bounce back to best. ANNDAR SHELLY (7) scored two back by a space then was last start always well back and could manage only a 14 length 7th at Hobart (27.24). Warrants plenty of respect. HAT TRICK HANNAH (4) cannot be overlooked following a recent top-three finish here at this distance."
        },
        "venue_id": "0eb684d3-8701-4458-b88e-a6b6a15582cb",
        "venue_name": "Launceston",
        "venue_state": "TAS",
        "venue_country": "AUS"
      },
      "77139d78-2067-4e51-b34f-846fb7e70266": {
        "race_id": "77139d78-2067-4e51-b34f-846fb7e70266",
        "race_name": "Race 10",
        "race_number": 10,
        "meeting_id": "7672104f-cbe3-4b61-8ca9-a6d34b6e4939",
        "meeting_name": "Hoosier Park",
        "category_id": "161d9be2-e909-4326-8c2c-35ed71fb460b",
        "advertised_start": {
          "seconds": 1748311140
        },
        "race_form": {
          "distance": 1609,
          "distance_type": {
            "id": "570775ae-09ec-42d5-989d-7c8f06366aa7",
            "name": "Metres",
            "short_name": "m"
          },
          "distance_type_id": "570775ae-09ec-42d5-989d-7c8f06366aa7",
          "track_condition": {
            "id": "10a14653-a33d-11e7-810d-0a1a4ae29bd2",
            "name": "Good",
            "short_name": "good"
          },
          "track_condition_id": "10a14653-a33d-11e7-810d-0a1a4ae29bd2",
          "additional_data": "{\"revealed_race_info\":{\"track_name\":\"Hoosier Park\",\"state\":\"IN\",\"country\":\"USA\",\"number\":10,\"race_name\":\"Race 10\",\"time\":\"2025-05-27T01:59:00Z\",\"class\":\"ISS-Elg3yC\",\"start_type\":\"Mobile\",\"prizemonies\":{\"total_value\":25000},\"localised_prizemonies\":{\"AUD\":{\"total_value\":25000},\"NZD\":{\"total_value\":27000}},\"rail_position\":\"\",\"track_direction\":\"Left\",\"track_surface\":\"All Weather\",\"group\":\"\",\"gait\":\"P\",\"track_home_straight_metres\":0,\"track_circumference\":0}}",
          "generated": 1,
          "silk_base_url": "drr38safykj6s.cloudfront.net"
        },
        "venue_id": "4f7d90ce-9d88-4bdd-9b78-3f0199b1afcd",
        "venue_name": "Hoosier Park",
        "venue_state": "IN",
        "venue_country": "USA"
      },
      "81560dea-c8fb-4ad4-bfc8-f2d0474e85c7": {
        "race_id": "81560dea-c8fb-4ad4-bfc8-f2d0474e85c7",
        "race_name": "In Hospitality Mdn Plate",
        "race_number": 1,
        "meeting_id": "043fbbaa-4135-4173-950a-9bef224956df",
        "meeting_name": "Seymour",
        "category_id": "4a2788f8-e825-4d36-9894-efd4baf1cfae",
        "advertised_start": {
          "seconds": 1748311200
        },
        "race_form": {
          "distance": 1000,
          "distance_type": {
            "id": "570775ae-09ec-42d5-989d-7c8f06366aa7",
            "name": "Metres",
            "short_name": "m"
          },
          "distance_type_id": "570775ae-09ec-42d5-989d-7c8f06366aa7",
          "track_condition": {
            "id": "11d7e662-487a-11ea-9d54-4689356d4521",
            "name": "Good4",
            "short_name": "good4"
          },
          "track_condition_id": "11d7e662-487a-11ea-9d54-4689356d4521",
          "weather": {
            "id": "5ba75165-3cec-11eb-88bb-36fbfdf5d97f",
            "name": "OCAST",
            "short_name": "ocast",
            "icon_uri": "OCAST"
          },
          "weather_id": "5ba75165-3cec-11eb-88bb-36fbfdf5d97f",
          "race_comment": "SUPERVISE (5) is an interesting runner resuming who returns for a new barn as a gelding. Fitter for three jump-outs and with good speed will take beating here if anywhere near best. TOO DARN COLD (6) returned with a fast finishing third in a richer race at Pakenham. Fitter and will be hard to beat on that. BREECHES (7) was well in the market in a far richer race on debut and safely held. Given a break and unbeaten in two jump-outs leading into this. Worth another chance. QUOIN (4) was also disappointing last time but rates very highly here on the placing two back here. Gets his chance to bounce. AIR CONTROL (1) has looked good on the track since a poor debut and is open to sharp improvement.",
          "additional_data": "{\"revealed_race_info\":{\"track_name\":\"Seymour\",\"state\":\"VIC\",\"country\":\"AUS\",\"number\":1,\"race_name\":\"In Hospitality Mdn Plate\",\"time\":\"2025-05-27T02:00:00Z\",\"class\":\"MDN\",\"start_type\":\"\",\"prizemonies\":{\"total_value\":27000},\"localised_prizemonies\":{\"AUD\":{\"10th\":675,\"1st\":14850,\"2nd\":4590,\"3rd\":2160,\"4th\":1215,\"5th\":810,\"6th\":675,\"7th\":675,\"8th\":675,\"9th\":675,\"total_value\":27000},\"NZD\":{\"10th\":729,\"1st\":16038,\"2nd\":4957,\"3rd\":2333,\"4th\":1312,\"5th\":875,\"6th\":729,\"7th\":729,\"8th\":729,\"9th\":729,\"total_value\":29160}},\"rail_position\":\"True Entire Circuit. (Pent: 5.06)\",\"track_direction\":\"Left\",\"track_surface\":\"Turf\",\"group\":\"\",\"gait\":\"Gallop\",\"track_home_straight_metres\":0,\"track_circumference\":1800}}",
          "generated": 1,
          "silk_base_url": "drr38safykj6s.cloudfront.net",
          "race_comment_alternative": "SUPERVISE (5) is an interesting runner resuming who returns for a new barn as a gelding. Fitter for three jump-outs and with good speed will take beating here if anywhere near best. TOO DARN COLD (6) returned with a fast finishing third in a richer race at Pakenham. Fitter and will be hard to beat on that. BREECHES (7) was well in the market in a far richer race on debut and safely held. Given a break and unbeaten in two jump-outs leading into this. Worth another chance. QUOIN (4) was also disappointing last time but rates very highly here on the placing two back here. Gets his chance to bounce. AIR CONTROL (1) has looked good on the track since a poor debut and is open to sharp improvement."
        },
        "venue_id": "b9553432-6532-444c-ac00-598f7217d6c2",
        "venue_name": "Seymour",
        "venue_state": "VIC",
        "venue_country": "AUS"
      },
      "997520e0-6554-439a-ab6c-7d67130df031": {
        "race_id": "997520e0-6554-439a-ab6c-7d67130df031",
        "race_name": "Race 9",
        "race_number": 9,
        "meeting_id": "543bfdef-26f7-4c3b-9ecd-41b03f17b9b5",
        "meeting_name": "Woodbine Mohawk Park",
        "category_id": "161d9be2-e909-4326-8c2c-35ed71fb460b",
        "advertised_start": {
          "seconds": 1748310540
        },
        "race_form": {
          "distance": 1609,
          "distance_type": {
            "id": "570775ae-09ec-42d5-989d-7c8f06366aa7",
            "name": "Metres",
            "short_name": "m"
          },
          "distance_type_id": "570775ae-09ec-42d5-989d-7c8f06366aa7",
          "track_condition": {
            "id": "1db9cab0-b747-11ea-80cf-6a390f79827e",
            "name": "Fast",
            "short_name": "fast"
          },
          "track_condition_id": "1db9cab0-b747-11ea-80cf-6a390f79827e",
          "weather": {
            "id": "08e5f78c-1a36-11eb-9269-cef03e67f1a3",
            "name": "FINE",
            "short_name": "fine",
            "icon_uri": "FINE"
          },
          "weather_id": "08e5f78c-1a36-11eb-9269-cef03e67f1a3",
          "race_comment": "GHOSTLY CASPER (3) won at this track two runs ago but couldn't repeat the dose at his latest appearance over 1609m at this track, beaten 9 metres. Will enjoy a nice run from this favourable starting position. Perfectly placed and is sure to prove tough to beat. SPARTAN GENERAL (6) was successful last start by 2 metres in a nice return to form at this track over 1609m. It doesn't get any easier but he is good enough to take this out. NASEY (5) is worth plenty of thought off a last-start win by 1.5 metres at this track over 1609m. LOCATELLI (8) must be included on the back of some solid recent form, most recently when fifth at this track over 1609m.",
          "additional_data": "{\"revealed_race_info\":{\"track_name\":\"Woodbine Mohawk Park\",\"state\":\"ON\",\"country\":\"CA\",\"number\":9,\"race_name\":\"Race 9\",\"time\":\"2025-05-27T01:49:00Z\",\"class\":\"\",\"start_type\":\"Mobile\",\"prizemonies\":{\"total_value\":31638},\"localised_prizemonies\":{\"AUD\":{\"total_value\":31638},\"NZD\":{\"total_value\":34169}},\"rail_position\":\"\",\"track_direction\":\"Left\",\"track_surface\":\"All Weather\",\"group\":\"\",\"gait\":\"T\",\"track_home_straight_metres\":0,\"track_circumference\":0}}",
          "generated": 1,
          "silk_base_url": "drr38safykj6s.cloudfront.net",
          "race_comment_alternative": "GHOSTLY CASPER (3) won at this track two runs ago but couldn't repeat the dose at his latest appearance over 1609m at this track, beaten 9 metres. Will enjoy a nice run from this favourable starting position. Perfectly placed and is sure to prove tough to beat. SPARTAN GENERAL (6) was successful last start by 2 metres in a nice return to form at this track over 1609m. It doesn't get any easier but he is good enough to take this out. NASEY (5) is worth plenty of thought off a last-start win by 1.5 metres at this track over 1609m. LOCATELLI (8) must be included on the back of some solid recent form, most recently when fifth at this track over 1609m."
        },
        "venue_id": "faf126e6-2146-4576-924c-930edcde0902",
        "venue_name": "Woodbine Mohawk Park",
        "venue_state": "ON",
        "venue_country": "CA"
      },
      "a455092e-071b-4412-8d5b-547832f77f83": {
        "race_id": "a455092e-071b-4412-8d5b-547832f77f83",
        "race_name": "Fischer Motors Maiden Stake Pr2 Division1",
        "race_number": 1,
        "meeting_id": "e2f6da86-0e67-4c39-b7b9-a1563e50acf4",
        "meeting_name": "Murray Bridge Straight",
        "category_id": "9daef0d7-bf3c-4f50-921d-8e818c60fe61",
        "advertised_start": {
          "seconds": 1748310300
        },
        "race_form": {
          "distance": 300,
          "distance_type": {
            "id": "570775ae-09ec-42d5-989d-7c8f06366aa7",
            "name": "Metres",
            "short_name": "m"
          },
          "distance_type_id": "570775ae-09ec-42d5-989d-7c8f06366aa7",
          "track_condition": {
            "id": "10a14653-a33d-11e7-810d-0a1a4ae29bd2",
            "name": "Good",
            "short_name": "good"
          },
          "track_condition_id": "10a14653-a33d-11e7-810d-0a1a4ae29bd2",
          "weather": {
            "id": "5ba75165-3cec-11eb-88bb-36fbfdf5d97f",
            "name": "OCAST",
            "short_name": "ocast",
            "icon_uri": "OCAST"
          },
          "weather_id": "5ba75165-3cec-11eb-88bb-36fbfdf5d97f",
          "race_comment": "HURRICANE EARL (1) ran above expectations on debut finishing in the placings when third (17.42) at this track. Boxed the fence this time. Much improved and can open his winning account. SLIP ME FIFTY (6) has been beaten for early speed lately, last time finishing fifth (24.90) in a Maiden at Gawler. Should be about the money. NEW BEAT LADY (2) copped a check in the run finishing out of the placings when a 5.5 lengths sixth (18.67) in a Maiden at this track. Has the ability and can atone with the right run. SKY CHASER (4) looks an each-way chance.",
          "additional_data": "{\"revealed_race_info\":{\"track_name\":\"Murray Bridge Straight\",\"state\":\"SA\",\"country\":\"AUS\",\"number\":1,\"race_name\":\"Fischer Motors Maiden Stake Pr2 Division1\",\"time\":\"2025-05-27T01:45:00Z\",\"class\":\"Maiden\",\"start_type\":\"\",\"prizemonies\":{\"total_value\":1015},\"localised_prizemonies\":{\"AUD\":{\"1st\":715,\"2nd\":200,\"3rd\":100,\"total_value\":1015},\"NZD\":{\"1st\":772,\"2nd\":216,\"3rd\":108,\"total_value\":1096}},\"rail_position\":\"\",\"track_direction\":\"Right\",\"track_surface\":\"All Weather\",\"group\":\"\",\"gait\":\"Gallop\",\"track_home_straight_metres\":0,\"track_circumference\":0}}",
          "generated": 1,
          "silk_base_url": "drr38safykj6s.cloudfront.net",
          "race_comment_alternative": "HURRICANE EARL (1) ran above expectations on debut finishing in the placings when third (17.42) at this track. Boxed the fence this time. Much improved and can open his winning account. SLIP ME FIFTY (6) has been beaten for early speed lately, last time finishing fifth (24.90) in a Maiden at Gawler. Should be about the money. NEW BEAT LADY (2) copped a check in the run finishing out of the placings when a 5.5 lengths sixth (18.67) in a Maiden at this track. Has the ability and can atone with the right run. SKY CHASER (4) looks an each-way chance."
        },
        "venue_id": "a2c7676e-474a-4a23-8465-d3ab553f0291",
        "venue_name": "Murray Bridge Straight",
        "venue_state": "SA",
        "venue_country": "AUS"
      },
      "b2f70aec-f181-44b7-b3ab-7673d31cfdf6": {
        "race_id": "b2f70aec-f181-44b7-b3ab-7673d31cfdf6",
        "race_name": "ACCELL THERAPY NZ",
        "race_number": 6,
        "meeting_id": "5ac0771b-b1a3-42ac-ab17-9f3557a56430",
        "meeting_name": "Manawatu",
        "category_id": "9daef0d7-bf3c-4f50-921d-8e818c60fe61",
        "advertised_start": {
          "seconds": 1748310600
        },
        "race_form": {
          "distance": 457,
          "distance_type": {
            "id": "570775ae-09ec-42d5-989d-7c8f06366aa7",
            "name": "Metres",
            "short_name": "m"
          },
          "distance_type_id": "570775ae-09ec-42d5-989d-7c8f06366aa7",
          "track_condition": {
            "id": "10a14653-a33d-11e7-810d-0a1a4ae29bd2",
            "name": "Good",
            "short_name": "good"
          },
          "track_condition_id": "10a14653-a33d-11e7-810d-0a1a4ae29bd2",
          "weather": {
            "id": "08e5f78c-1a36-11eb-9269-cef03e67f1a3",
            "name": "FINE",
            "short_name": "fine",
            "icon_uri": "FINE"
          },
          "weather_id": "08e5f78c-1a36-11eb-9269-cef03e67f1a3",
          "race_comment": "BIG TIME TOBY (6) is a smart type who sailed across from an outside draw to score an all the way win (30.44) at Wanganui in Class 4 over 520m. Has never missed the frame here from three starts. One of the key runners again. MORE MAGIC (8) was in the minors two back (38.84) at this track but ran below best last time at Wanganui Straight, finishing 6th. Will give the top chances plenty to think about. BIG TIME TAMA (2) turned in a fair 5th placed finish last time at Wanganui over 520m (30.78). Solid record here at the distance winning five races. Better than the latest run and deserves another chance. REMOVE ALL DOUBT (7) has ability and can feature with the right run after missing a cheque here most recently.",
          "additional_data": "{\"revealed_race_info\":{\"track_name\":\"Manawatu\",\"state\":\"NZ\",\"country\":\"NZ\",\"number\":6,\"race_name\":\"ACCELL THERAPY NZ\",\"time\":\"2025-05-27T01:50:00Z\",\"class\":\"C4\",\"start_type\":\"\",\"prizemonies\":{\"total_value\":5092},\"localised_prizemonies\":{\"AUD\":{\"total_value\":5000},\"NZD\":{\"total_value\":5500}},\"rail_position\":\"\",\"track_direction\":\"Left\",\"track_surface\":\"All Weather\",\"group\":\"Grade\",\"gait\":\"\",\"track_home_straight_metres\":0,\"track_circumference\":0}}",
          "generated": 1,
          "silk_base_url": "drr38safykj6s.cloudfront.net",
          "race_comment_alternative": "BIG TIME TOBY (6) is a smart type who sailed across from an outside draw to score an all the way win (30.44) at Wanganui in Class 4 over 520m. Has never missed the frame here from three starts. One of the key runners again. MORE MAGIC (8) was in the minors two back (38.84) at this track but ran below best last time at Wanganui Straight, finishing 6th. Will give the top chances plenty to think about. BIG TIME TAMA (2) turned in a fair 5th placed finish last time at Wanganui over 520m (30.78). Solid record here at the distance winning five races. Better than the latest run and deserves another chance. REMOVE ALL DOUBT (7) has ability and can feature with the right run after missing a cheque here most recently."
        },
        "venue_id": "809963b5-79b6-45c0-a1e8-5c4d80f890bd",
        "venue_name": "Manawatu",
        "venue_state": "NZ",
        "venue_country": "NZ"
      }
    }
  },
  "message": "Next 10 races from each category"
}
